iotc/__init__.py
iotc/generate-sas-creds.py
iotc/models.py
iotc/aio/__init__.py
iotc/test/__init__.py
iotc/test/utils.py
iotc/test/async/__init__.py
iotc/test/async/test_advanced.py
iotc/test/async/test_keys.py
iotc/test/async/test_listeners.py
iotc/test/sync/__init__.py
iotc/test/sync/test_advanced.py
iotc/test/sync/test_keys.py
iotc/test/sync/test_listeners.py
iotc-1.1.3.dist-info/LICENSE
iotc-1.1.3.dist-info/METADATA
iotc-1.1.3.dist-info/WHEEL
iotc-1.1.3.dist-info/top_level.txt
iotc-1.1.3.dist-info/RECORD
