Metadata-Version: 2.1
Name: iotc
Version: 1.1.3
Summary: Azure IoT Central device client for Python
Home-page: https://github.com/iot-for-all/iotc-python-client
Author: Luca Druda
Author-email: ludruda@microsoft.com
License: MIT
Keywords: iot,azure,iotcentral
Platform: UNKNOWN
Classifier: License :: OSI Approved :: MIT License
Classifier: Programming Language :: Python
Classifier: Programming Language :: Python :: 3
Classifier: Programming Language :: Python :: 3.6
Classifier: Programming Language :: Python :: 3.7
Classifier: Programming Language :: Python :: 3.8
Classifier: Programming Language :: Python :: 3.9
